LICENSE
skillflux/django/__init__.py
skillflux/django/apps.py
skillflux/django/migrations/0001_initial.py
skillflux/django/migrations/__init__.py
skillflux/django/models.py
skillflux/django/tests.py
django_skillflux-1.0.dev2.dist-info/LICENSE
django_skillflux-1.0.dev2.dist-info/WHEEL
django_skillflux-1.0.dev2.dist-info/METADATA
django_skillflux-1.0.dev2.dist-info/RECORD
